westac_statistics/__init__.py
westac_statistics/case_one_gui.py
westac_statistics/corpus_fast_tokenizer.py
westac_statistics/corpus_parser.py
westac_statistics/metadata_parser.py
westac_statistics/tf_idf_calculator.py
westac_statistics/westac_histogram.py
westac_statistics-0.4.0.dist-info/METADATA
westac_statistics-0.4.0.dist-info/WHEEL
westac_statistics-0.4.0.dist-info/RECORD
