Metadata-Version: 2.1
Name: westac-statistics
Version: 0.4.0
Summary: Python statistics package for WeStAc, and the Swedish parliamentary proceedings
Home-page: https://github.com/TomasSkotare/westac-statistics
License: MIT
Author: TomasSkotare
Author-email: tomas.skotare@umu.se
Requires-Python: >=3.11.0,<3.12.0
Classifier: License :: OSI Approved :: MIT License
Classifier: Programming Language :: Python :: 3
Classifier: Programming Language :: Python :: 3.11
Requires-Dist: bs4
Requires-Dist: nltk
Requires-Dist: numba
Requires-Dist: numpy
Requires-Dist: pandas
Requires-Dist: plotly
Requires-Dist: scipy
Requires-Dist: tqdm
Project-URL: Repository, https://github.com/TomasSkotare/westac-statistics
